preocr/__init__.py
preocr/constants.py
preocr/exceptions.py
preocr/py.typed
preocr/reason_codes.py
preocr/version.py
preocr-0.7.0.dist-info/licenses/LICENSE
preocr-0.7.0.dist-info/METADATA
preocr-0.7.0.dist-info/WHEEL
preocr-0.7.0.dist-info/top_level.txt
preocr-0.7.0.dist-info/RECORD
