Metadata-Version: 2.4
Name: preocr
Version: 0.7.0
Summary: A fast, CPU-only library that intelligently detects whether files need OCR processing before expensive OCR operations. Uses hybrid adaptive pipeline for 92-95% accuracy.
Author: PreOCR Contributors
License-Expression: Apache-2.0
Project-URL: Homepage, https://github.com/yuvaraj3855/preocr
Project-URL: Documentation, https://github.com/yuvaraj3855/preocr#readme
Project-URL: Repository, https://github.com/yuvaraj3855/preocr
Project-URL: Issues, https://github.com/yuvaraj3855/preocr/issues
Keywords: ocr,document,detection,preprocessing,file-analysis,layout-analysis,pdf-analysis,text-extraction,document-processing,opencv,computer-vision
Classifier: Development Status :: 3 - Alpha
Classifier: Intended Audience :: Developers
Classifier: Programming Language :: Python :: 3
Classifier: Programming Language :: Python :: 3.9
Classifier: Programming Language :: Python :: 3.10
Classifier: Programming Language :: Python :: 3.11
Classifier: Topic :: Software Development :: Libraries :: Python Modules
Classifier: Topic :: Text Processing
Classifier: Topic :: Multimedia :: Graphics
Classifier: Topic :: Scientific/Engineering :: Image Recognition
Classifier: Operating System :: OS Independent
Requires-Python: >=3.9
License-File: LICENSE
Requires-Dist: python-magic>=0.4.27
Requires-Dist: pdfplumber>=0.10.0
Requires-Dist: python-docx>=1.1.0
Requires-Dist: python-pptx>=0.6.23
Requires-Dist: openpyxl>=3.1.0
Requires-Dist: Pillow>=10.0.0
Requires-Dist: beautifulsoup4>=4.12.0
Provides-Extra: dev
Requires-Dist: pytest>=7.4.0; extra == "dev"
Requires-Dist: pytest-cov>=4.1.0; extra == "dev"
Requires-Dist: black>=23.0.0; extra == "dev"
Requires-Dist: ruff>=0.1.0; extra == "dev"
Requires-Dist: mypy>=1.5.0; extra == "dev"
Requires-Dist: pre-commit>=3.5.0; extra == "dev"
Provides-Extra: layout-refinement
Requires-Dist: opencv-python-headless>=4.8.0; extra == "layout-refinement"
Requires-Dist: numpy>=1.24.0; extra == "layout-refinement"
Provides-Extra: batch
Requires-Dist: tqdm>=4.65.0; extra == "batch"
Dynamic: license-file
